curly_brace/__init__.py
curly_brace/_modidx.py
curly_brace/core.py
curly_brace-0.0.3.dist-info/LICENSE
curly_brace-0.0.3.dist-info/METADATA
curly_brace-0.0.3.dist-info/WHEEL
curly_brace-0.0.3.dist-info/entry_points.txt
curly_brace-0.0.3.dist-info/top_level.txt
curly_brace-0.0.3.dist-info/RECORD
