Metadata-Version: 2.1
Name: curly-brace
Version: 0.0.3
Summary: pip installable package of the git repo https://github.com/iruletheworld/matplotlib-curly-brace credit to 高斯羽 博士 Dr. GAO, Siyu
Home-page: https://github.com/opimwue/curly_brace
Author: Magnus Maichle
Author-email: magnus.maichle@uni-wuerzburg.de
License: Apache Software License 2.0
Keywords: nbdev jupyter notebook python
Classifier: Development Status :: 4 - Beta
Classifier: Intended Audience :: Developers
Classifier: Natural Language :: English
Classifier: Programming Language :: Python :: 3.7
Classifier: Programming Language :: Python :: 3.8
Classifier: Programming Language :: Python :: 3.9
Classifier: Programming Language :: Python :: 3.10
Classifier: License :: OSI Approved :: Apache Software License
Requires-Python: >=3.7
License-File: LICENSE
Provides-Extra: dev
